wpmaker/__init__.py
webpage_maker-1.1.1.dist-info/LICENSE
webpage_maker-1.1.1.dist-info/METADATA
webpage_maker-1.1.1.dist-info/WHEEL
webpage_maker-1.1.1.dist-info/top_level.txt
webpage_maker-1.1.1.dist-info/RECORD
