Metadata-Version: 2.1
Name: webpage-maker
Version: 1.1.1
Summary: A Python library for generating (rendering) static HTML web pages
Home-page: https://gitee.com/wang-chenfan/webpage-maker
Author: Chenfan Wang
Author-email: admin@wcfstudio.cn
License: UNKNOWN
Platform: UNKNOWN
Classifier: Development Status :: 2 - Pre-Alpha
Classifier: Intended Audience :: Developers
Classifier: Intended Audience :: Information Technology
Classifier: License :: OSI Approved :: MIT License
Classifier: Programming Language :: Python
Classifier: Programming Language :: Python :: 2
Classifier: Programming Language :: Python :: 3
Classifier: Programming Language :: Python :: 3.6
Classifier: Programming Language :: Python :: 3.7
Classifier: Programming Language :: Python :: 3.8
Classifier: Programming Language :: Python :: 3.9
